memepack_builder/BEPackBuilder.py
memepack_builder/JEPackBuilder.py
memepack_builder/ModuleChecker.py
memepack_builder/PlatformChecker.py
memepack_builder/__init__.py
memepack_builder/__main__.py
memepack_builder/wrapper.py
memepack_builder/_internal/__init__.py
memepack_builder/_internal/cli.py
memepack_builder/_internal/error_code.py
memepack_builder/_internal/module_classifier.py
memepack_builder/_internal/pack_builder.py
memepack_builder-0.2.4.dist-info/LICENSE
memepack_builder-0.2.4.dist-info/METADATA
memepack_builder-0.2.4.dist-info/WHEEL
memepack_builder-0.2.4.dist-info/top_level.txt
memepack_builder-0.2.4.dist-info/RECORD
