Metadata-Version: 2.1
Name: memepack-builder
Version: 0.2.4
Summary: A tool for packaging Memefied Chinese resource pack
Home-page: https://github.com/Teahouse-Studios/memepack-builder
Author: MysticNebula70
Author-email: mysticnebula70@teahou.se
License: UNKNOWN
Platform: UNKNOWN
Classifier: Programming Language :: Python :: 3.9
Classifier: License :: OSI Approved :: Apache Software License
Classifier: Operating System :: OS Independent
Requires-Python: >=3.9
License-File: LICENSE
